sonarcal/__init__.py
sonarcal/__main__.py
sonarcal/calculate_gains.py
sonarcal/calibration_data.py
sonarcal/calibration_gui.py
sonarcal/configuration.py
sonarcal/controller.py
sonarcal/datagram_processor.py
sonarcal/dialog_config.py
sonarcal/dialog_results.py
sonarcal/echogram_plotter.py
sonarcal/file_ops.py
sonarcal/gui_utils.py
sonarcal/rewrite_raw_file.py
sonarcal/utils.py
sonarcal/assets/logo.png
sonarcal/raw_parser/__init__.py
sonarcal/raw_parser/simrad_parsers.py
sonarcal/raw_parser/simrad_raw_file.py
sonarcal/offline-docs/404.html
sonarcal/offline-docs/index.html
sonarcal/offline-docs/sitemap.xml
sonarcal/offline-docs/sitemap.xml.gz
sonarcal/offline-docs/technical.html
sonarcal/offline-docs/assets/Beam_example.png
sonarcal/offline-docs/assets/logo.svg
sonarcal/offline-docs/assets/screenshot.png
sonarcal/offline-docs/assets/images/favicon.png
sonarcal/offline-docs/assets/javascripts/bundle.79ae519e.min.js
sonarcal/offline-docs/assets/javascripts/bundle.79ae519e.min.js.map
sonarcal/offline-docs/assets/javascripts/lunr/tinyseg.js
sonarcal/offline-docs/assets/javascripts/lunr/wordcut.js
sonarcal/offline-docs/assets/javascripts/lunr/min/lunr.ar.min.js
sonarcal/offline-docs/assets/javascripts/lunr/min/lunr.da.min.js
sonarcal/offline-docs/assets/javascripts/lunr/min/lunr.de.min.js
sonarcal/offline-docs/assets/javascripts/lunr/min/lunr.du.min.js
sonarcal/offline-docs/assets/javascripts/lunr/min/lunr.el.min.js
sonarcal/offline-docs/assets/javascripts/lunr/min/lunr.es.min.js
sonarcal/offline-docs/assets/javascripts/lunr/min/lunr.fi.min.js
sonarcal/offline-docs/assets/javascripts/lunr/min/lunr.fr.min.js
sonarcal/offline-docs/assets/javascripts/lunr/min/lunr.he.min.js
sonarcal/offline-docs/assets/javascripts/lunr/min/lunr.hi.min.js
sonarcal/offline-docs/assets/javascripts/lunr/min/lunr.hu.min.js
sonarcal/offline-docs/assets/javascripts/lunr/min/lunr.hy.min.js
sonarcal/offline-docs/assets/javascripts/lunr/min/lunr.it.min.js
sonarcal-1.1.3.dist-info/METADATA
sonarcal-1.1.3.dist-info/WHEEL
sonarcal-1.1.3.dist-info/entry_points.txt
sonarcal-1.1.3.dist-info/licenses/LICENSE
sonarcal-1.1.3.dist-info/RECORD
