Metadata-Version: 2.4
Name: sonarcal
Version: 1.1.3
Summary: Software to facilitate standard-sphere calibration of omni-directional sonars
Project-URL: Homepage, https://github.com/Aqualyd-Limited/sonarCal
Project-URL: Issues, https://github.com/Aqualyd-Limited/sonarCal/issues
Project-URL: Documentation, https://aqualyd-limited.github.io/sonarCal/
Project-URL: Repository, https://github.com/Aqualyd-Limited/sonarCal
Author: Gavin Macaulay
License: MIT License
License-File: LICENSE
Keywords: acoustic,calibration,sonar
Classifier: Development Status :: 3 - Alpha
Classifier: Intended Audience :: Science/Research
Classifier: License :: OSI Approved :: MIT License
Classifier: Operating System :: OS Independent
Classifier: Programming Language :: Python :: 3
Classifier: Programming Language :: Python :: 3.11
Classifier: Programming Language :: Python :: 3.12
Classifier: Programming Language :: Python :: 3.13
Classifier: Programming Language :: Python :: 3.14
Classifier: Topic :: Scientific/Engineering
Requires-Python: >=3.11
Requires-Dist: arrow
Requires-Dist: construct
Requires-Dist: h5py
Requires-Dist: humanize
Requires-Dist: matplotlib
Requires-Dist: natsort
Requires-Dist: numpy
Requires-Dist: pandas
Requires-Dist: pillow
Requires-Dist: platformdirs
Requires-Dist: pywin32; platform_system == 'Windows'
Requires-Dist: scipy
Requires-Dist: sv-ttk
Provides-Extra: dev
Requires-Dist: mkdocs-material; extra == 'dev'
Requires-Dist: pytest; extra == 'dev'
Requires-Dist: twine; extra == 'dev'
